cdk_lambda_layer_zip/__init__.py
cdk_lambda_layer_zip/py.typed
cdk_lambda_layer_zip/_jsii/__init__.py
cdk_lambda_layer_zip/_jsii/cdk-lambda-layer-zip@2.0.343.jsii.tgz
cdk_lambda_layer_zip-2.0.343.dist-info/LICENSE
cdk_lambda_layer_zip-2.0.343.dist-info/METADATA
cdk_lambda_layer_zip-2.0.343.dist-info/WHEEL
cdk_lambda_layer_zip-2.0.343.dist-info/top_level.txt
cdk_lambda_layer_zip-2.0.343.dist-info/RECORD
